{"loss": 0.20776423811912537, "mean_accuracy": 0.9345703125, "time_this_iter_s": 16.851111888885498, "done": false, "timesteps_total": null, "episodes_total": null, "training_iteration": 1, "experiment_id": "d93fe6d845da42279704860fb38352a3", "date": "2021-05-26_16-29-36", "timestamp": 1622039376, "time_total_s": 16.851111888885498, "pid": 11966, "hostname": "Timos-MacBook-Pro-2.local", "node_ip": "192.168.2.103", "config": {"layer_1_size": 128, "layer_2_size": 256, "lr": 0.0031354923020492954, "batch_size": 128, "mlflow": {"experiment_name": "/Users/timo.bohnstedt@fau.de/Jiggsaw_test", "tracking_uri": "databricks"}}, "time_since_restore": 16.851111888885498, "timesteps_since_restore": 0, "iterations_since_restore": 1, "trial_id": "bfcc3_00000"}
{"loss": 0.1946648210287094, "mean_accuracy": 0.9443359375, "time_this_iter_s": 7.842988014221191, "done": false, "timesteps_total": null, "episodes_total": null, "training_iteration": 2, "experiment_id": "d93fe6d845da42279704860fb38352a3", "date": "2021-05-26_16-29-44", "timestamp": 1622039384, "time_total_s": 24.69409990310669, "pid": 11966, "hostname": "Timos-MacBook-Pro-2.local", "node_ip": "192.168.2.103", "config": {"layer_1_size": 128, "layer_2_size": 256, "lr": 0.0031354923020492954, "batch_size": 128, "mlflow": {"experiment_name": "/Users/timo.bohnstedt@fau.de/Jiggsaw_test", "tracking_uri": "databricks"}}, "time_since_restore": 24.69409990310669, "timesteps_since_restore": 0, "iterations_since_restore": 2, "trial_id": "bfcc3_00000"}
{"loss": 0.22710564732551575, "mean_accuracy": 0.9408203363418579, "time_this_iter_s": 7.9011242389678955, "done": false, "timesteps_total": null, "episodes_total": null, "training_iteration": 3, "experiment_id": "d93fe6d845da42279704860fb38352a3", "date": "2021-05-26_16-29-52", "timestamp": 1622039392, "time_total_s": 32.595224142074585, "pid": 11966, "hostname": "Timos-MacBook-Pro-2.local", "node_ip": "192.168.2.103", "config": {"layer_1_size": 128, "layer_2_size": 256, "lr": 0.0031354923020492954, "batch_size": 128, "mlflow": {"experiment_name": "/Users/timo.bohnstedt@fau.de/Jiggsaw_test", "tracking_uri": "databricks"}}, "time_since_restore": 32.595224142074585, "timesteps_since_restore": 0, "iterations_since_restore": 3, "trial_id": "bfcc3_00000"}
{"loss": 0.2259025126695633, "mean_accuracy": 0.9478515386581421, "time_this_iter_s": 7.787791728973389, "done": false, "timesteps_total": null, "episodes_total": null, "training_iteration": 4, "experiment_id": "d93fe6d845da42279704860fb38352a3", "date": "2021-05-26_16-29-59", "timestamp": 1622039399, "time_total_s": 40.383015871047974, "pid": 11966, "hostname": "Timos-MacBook-Pro-2.local", "node_ip": "192.168.2.103", "config": {"layer_1_size": 128, "layer_2_size": 256, "lr": 0.0031354923020492954, "batch_size": 128, "mlflow": {"experiment_name": "/Users/timo.bohnstedt@fau.de/Jiggsaw_test", "tracking_uri": "databricks"}}, "time_since_restore": 40.383015871047974, "timesteps_since_restore": 0, "iterations_since_restore": 4, "trial_id": "bfcc3_00000"}
{"loss": 0.2220717966556549, "mean_accuracy": 0.953125, "time_this_iter_s": 7.78428316116333, "done": false, "timesteps_total": null, "episodes_total": null, "training_iteration": 5, "experiment_id": "d93fe6d845da42279704860fb38352a3", "date": "2021-05-26_16-30-07", "timestamp": 1622039407, "time_total_s": 48.167299032211304, "pid": 11966, "hostname": "Timos-MacBook-Pro-2.local", "node_ip": "192.168.2.103", "config": {"layer_1_size": 128, "layer_2_size": 256, "lr": 0.0031354923020492954, "batch_size": 128, "mlflow": {"experiment_name": "/Users/timo.bohnstedt@fau.de/Jiggsaw_test", "tracking_uri": "databricks"}}, "time_since_restore": 48.167299032211304, "timesteps_since_restore": 0, "iterations_since_restore": 5, "trial_id": "bfcc3_00000"}
{"loss": 0.3012967109680176, "mean_accuracy": 0.94921875, "time_this_iter_s": 7.826014041900635, "done": false, "timesteps_total": null, "episodes_total": null, "training_iteration": 6, "experiment_id": "d93fe6d845da42279704860fb38352a3", "date": "2021-05-26_16-30-15", "timestamp": 1622039415, "time_total_s": 55.99331307411194, "pid": 11966, "hostname": "Timos-MacBook-Pro-2.local", "node_ip": "192.168.2.103", "config": {"layer_1_size": 128, "layer_2_size": 256, "lr": 0.0031354923020492954, "batch_size": 128, "mlflow": {"experiment_name": "/Users/timo.bohnstedt@fau.de/Jiggsaw_test", "tracking_uri": "databricks"}}, "time_since_restore": 55.99331307411194, "timesteps_since_restore": 0, "iterations_since_restore": 6, "trial_id": "bfcc3_00000"}
{"loss": 0.27197617292404175, "mean_accuracy": 0.9486328363418579, "time_this_iter_s": 7.883092880249023, "done": false, "timesteps_total": null, "episodes_total": null, "training_iteration": 7, "experiment_id": "d93fe6d845da42279704860fb38352a3", "date": "2021-05-26_16-30-23", "timestamp": 1622039423, "time_total_s": 63.87640595436096, "pid": 11966, "hostname": "Timos-MacBook-Pro-2.local", "node_ip": "192.168.2.103", "config": {"layer_1_size": 128, "layer_2_size": 256, "lr": 0.0031354923020492954, "batch_size": 128, "mlflow": {"experiment_name": "/Users/timo.bohnstedt@fau.de/Jiggsaw_test", "tracking_uri": "databricks"}}, "time_since_restore": 63.87640595436096, "timesteps_since_restore": 0, "iterations_since_restore": 7, "trial_id": "bfcc3_00000"}
{"loss": 0.31648510694503784, "mean_accuracy": 0.948046863079071, "time_this_iter_s": 7.925215005874634, "done": false, "timesteps_total": null, "episodes_total": null, "training_iteration": 8, "experiment_id": "d93fe6d845da42279704860fb38352a3", "date": "2021-05-26_16-30-31", "timestamp": 1622039431, "time_total_s": 71.8016209602356, "pid": 11966, "hostname": "Timos-MacBook-Pro-2.local", "node_ip": "192.168.2.103", "config": {"layer_1_size": 128, "layer_2_size": 256, "lr": 0.0031354923020492954, "batch_size": 128, "mlflow": {"experiment_name": "/Users/timo.bohnstedt@fau.de/Jiggsaw_test", "tracking_uri": "databricks"}}, "time_since_restore": 71.8016209602356, "timesteps_since_restore": 0, "iterations_since_restore": 8, "trial_id": "bfcc3_00000"}
{"loss": 0.2789781987667084, "mean_accuracy": 0.9537109136581421, "time_this_iter_s": 7.966202020645142, "done": false, "timesteps_total": null, "episodes_total": null, "training_iteration": 9, "experiment_id": "d93fe6d845da42279704860fb38352a3", "date": "2021-05-26_16-30-39", "timestamp": 1622039439, "time_total_s": 79.76782298088074, "pid": 11966, "hostname": "Timos-MacBook-Pro-2.local", "node_ip": "192.168.2.103", "config": {"layer_1_size": 128, "layer_2_size": 256, "lr": 0.0031354923020492954, "batch_size": 128, "mlflow": {"experiment_name": "/Users/timo.bohnstedt@fau.de/Jiggsaw_test", "tracking_uri": "databricks"}}, "time_since_restore": 79.76782298088074, "timesteps_since_restore": 0, "iterations_since_restore": 9, "trial_id": "bfcc3_00000"}
{"loss": 0.30423396825790405, "mean_accuracy": 0.9501953125, "time_this_iter_s": 8.09816598892212, "done": false, "timesteps_total": null, "episodes_total": null, "training_iteration": 10, "experiment_id": "d93fe6d845da42279704860fb38352a3", "date": "2021-05-26_16-30-47", "timestamp": 1622039447, "time_total_s": 87.86598896980286, "pid": 11966, "hostname": "Timos-MacBook-Pro-2.local", "node_ip": "192.168.2.103", "config": {"layer_1_size": 128, "layer_2_size": 256, "lr": 0.0031354923020492954, "batch_size": 128, "mlflow": {"experiment_name": "/Users/timo.bohnstedt@fau.de/Jiggsaw_test", "tracking_uri": "databricks"}}, "time_since_restore": 87.86598896980286, "timesteps_since_restore": 0, "iterations_since_restore": 10, "trial_id": "bfcc3_00000"}
